[
  {
    "product_id": 1,
    "product_name": "ุงูุฏููู ุงูุชูููุฏู ููุฑุจุญ ูู ุงูููุชุฌุงุช ุงูุฑูููุฉ",
    "product_name_en": "Introductory Guide to Profiting from Digital Products",
    "product_image": "/images/products/introductory-guide.jpg",
    "description": "ูู ููุฑุช ููููุง ููุด ุบูุฑู ูุฑุจุญ ูู ุงูุฅูุชุฑูุช ุจุณูููุฉ ุจูููุง ุฃูุช ูุง ุฒูุช ูุญุชุงุฑ ูู ุฃูู ุชุจุฏุฃุ\n\nูุฐุง ุงูุฏููู ุงูุชูููุฏู ุจูุณุงุนุฏู ุชููู ุงูุฎุทูุงุช ุงูุฃุณุงุณูุฉ ูุจูุงุก ููุชุฌ ุฑููู ูุงุฌุญ ูุจูุน ุญุชู ูุฃูุช ูุงูู ๐ด๐ฐ\n\nุฑุญ ุชุชุนูู ููู:\n\nโข ููู ุชุฎุชุงุฑ ููุฑุฉ ููุชุฌ ุฑููู ูุฑุจุญุฉ\nโข ุงูุฃุณุงุณูุงุช ุงููู ูุงุฒู ุชุจูู ุนูููุง ูุชุฌุฑู ุฃู ุตูุญุชู\nโข ููู ุชุณููู ุตุญ ุจุฏูู ูุง ุชุถูุน ููุชู ููุงูู\n\n๐ ููุงุญุธูุฉ: ูุฐุง ุงููุชุงุจ ูู ููุฏูุฉ ุจุณูุทุฉ ูู ุงููุชุงุจ ุงููุงูู \"ุฎุทุฉ ุจูุงุก ูุดุฑูุนู ุงูุฑููู ูู ุงูุตูุฑ\"ุ ุงููู ููู ุฑูุงุจุท ูุจุงุดุฑุฉ ูุฃุฏูุงุชุ ูููุงูุน ุนูููุฉ ุชุณุงุนุฏู ุชุจุฏุฃ ููุฑูุง ๐",
    "price": 0,
    "originalPrice": 30,
    "currency": "SAR",
    "download_url": "https://cix55jnodh8jj42w.public.blob.vercel-storage.com/%D8%A7%D9%84%D9%85%D9%86%D8%AA%D8%AC%D8%A7%D8%AA/%D8%A7%D9%84%D8%AF%D9%84%D9%8A%D9%84%20%D8%A7%D9%84%D8%AA%D9%85%D9%87%D9%8A%D8%AF%D9%8A%20%D9%84%D9%84%D9%85%D9%86%D8%AA%D8%AC%D8%A7%D8%AA%20%D8%A7%D9%84%D8%B1%D9%82%D9%85%D9%8A%D8%A9%20%281%29.pdf",
    "filename": "introductory-guide.pdf",
    "file_size_mb": 5,
    "category": "ebooks",
    "tags": [
      "ุฏููู",
      "ููุชุฌุงุช-ุฑูููุฉ",
      "ูุจุชุฏุฆูู",
      "ุฑุจุญ-ุงูููุงูู"
    ],
    "active": true,
    "rating": 4.8,
    "buyers": "ุนุฏุฏ ูุฑุงุช ุงูุดุฑุงุก: 300+",
    "featured": true,
    "isFree": true
  },
  {
    "product_id": 2,
    "product_name": "ุงูุฑุจุญ ูู ุงูููุชุฌุงุช ุงูุฑูููุฉ",
    "product_name_en": "Profit from Digital Products",
    "product_image": "/images/products/digital-products-profit.jpg",
    "description": "ุชุชุนุจ ุจุงูุดุบู ูู ูููโฆ ููู ุฏุงูู ุชุณุฃู ููุณู:\n\n\"ููุด ุบูุฑู ูุฑุจุญ ูู ุงูุฅูุชุฑูุช ูุฃูุง ูุฃุ\" ๐ญ\n\nุงูุฌูุงุจ ุจุณูุท: ูุฃููู ุนุฑููุง ููู ูุญูููู ููุงุฑุงุชูู ุฅูู ููุชุฌุงุช ุฑูููุฉ ุชุจูุน ุนููู ุญุชู ููู ูุงูููู ๐ด๐ฐ\n\nูุงูุขูุ ูุฐุง ุงููุชุงุจ ุจูุนุทูู ุงูุฎุทุฉ ุงููุงููุฉ ุฎุทูุฉ ุจุฎุทูุฉ ูุชุจุฏุฃ ูุดุฑูุนู ุงูุฑููู ุงูุฃูู ูุชุจูู ุฏุฎู ุญูููู ูู ุงูุฅูุชุฑูุช ๐\n\n๐ ุฃุถูู ูู ุฃูู ุจุนุฏ ูุฑุงุกุฉ ูุฐุง ุงููุชุงุจุ ุณุชูุชูู ุฎุฑูุทุฉ ุทุฑูู ูุงูุนูุฉ ููุฑุจุญ ูู ุงูุฅูุชุฑูุช.\n\n๐ ูุง ุงูุฐู ุณุชุชุนููู:\nโข ูุง ูู ุงูููุชุฌุงุช ุงูุฑูููุฉ ูููุงุฐุง ุชุนุชุจุฑ ุฃุณุฑุน ูุฃุฐูู ุทุฑููุฉ ูุจูุงุก ุฏุฎู ูุณุชูุฑ\nโข ุฃููุงุน ุงูููุชุฌุงุช ุงูุฑูููุฉ ุงูุฃูุซุฑ ูุจูุนูุง (ูุชุจุ ููุฑุณุงุชุ ููุงูุจุ ุฃุฏูุงุช ูููุชุงุฌุ ูุคุซุฑุงุช ุตูุชูุฉ)\nโข ููู ุชุฎุชุงุฑ ููุฑุฉ ููุชุฌ ุชุถูู ูู ุงููุจูุนุงุช ูุชูุงุณุจ ููุงุฑุงุชู\nโข ุงูุฃุฏูุงุช ูุงูููุตุงุช ุงูุชู ูุญุชุงุฌูุง ุฃู ุดุฎุต ููุงูุทูุงู ููุฑูุง\nโข ุทุฑููุฉ ุฅูุดุงุก ูุชุฌุฑู ุงูุฑููู ูุจุฏุก ุงูุจูุน ุฎูุงู ููู ูุงุญุฏ ููุท\nโข ุฃุณุงููุจ ุงูุชุณููู ุงูุญุฏูุซุฉ ุนุจุฑ TikTok ูInstagram ูSEO ูุฌุฐุจ ูุฆุงุช ุงูุนููุงุก\nโข ุฃุณุฑุงุฑ ุจูุงุก ุฏุฎู ุณูุจู ูุฌูุจ ูู ุงููุงู ุญุชู ุฃุซูุงุก ูููู!\n\n๐ ูููุฒุงุช ุงููุชุงุจ:\n๐ง ุณูู ููุงุถุญ: ูุง ููุณูุฉุ ููุท ุฎุทูุงุช ุนูููุฉ ุญููููุฉ\n๐ผ ูุฎุชุตุฑ ููุนูุงู: ูู ุตูุญุฉ ุชุนุทูู ูุชูุฌุฉ\n๐ฑ ุจุตูุบุฉ PDF โ ููููู ูุฑุงุกุชู ุนูู ุฃู ุฌูุงุฒ ููุฑ ุงูุฏูุน\n๐ฅ ุชุตููู ุงุญุชุฑุงูู ููุบุฉ ุจุณูุทุฉ ุชูุงุณุจ ูู ูุฆุงุช ุงููุฑุงุก\n๐ฌ ูุจูู ุนูู ุฎุจุฑุฉ ูุชุฌุงุฑุจ ุญููููุฉ ูู ุงูุจูุน ุงูุฑููู\n\n๐งฉ ุชูุงุตูู ุงูููุชุฌ:\n๐ ุงูุตูุบุฉ PDF\n๐ฅ ุงูุชุญููู ููุฑู ุจุนุฏ ุงูุฏูุน\nโฑ๏ธ ูุฏุฉ ุงููุฑุงุกุฉ ุญูุงูู 20 ุฏูููุฉ\n๐ ุงูุตูุญุงุช ุชูุฑูุจูุง 10 ุตูุญุงุช ูุฑูุฒุฉ ุนูู ุงูุงูู ููุท\n๐ ุงููุบุฉ ุงูุนุฑุจูุฉ\n๐ฏ ููุงุณุจ ูููู ูู ูุฑูุฏ ุจุฏุก ูุดุฑูุน ุฑููู ุฃู ุฏุฎู ุฅุถุงูู\n\n๐ ููุงุฐุง ูุฐุง ุงููุชุงุจ ูุฎุชููุ\nูุฃู ูุฐุง ุงููุชุงุจ ูุง ูุจูุน ูู ุฃุญูุงููุงุ ุจู ููุฏูู ูู ุฎุทุฉ ุฌุงูุฒุฉ ูุฏุฑูุณุฉุ ุณุชุนุฑู ูู ุฎูุงููุง ููู:\nโข ุชุทูู ููุชุฌู ุงูุฑููู ุงูุฃูู ุจุฎุทูุงุช ุจุณูุทุฉ\nโข ุชุจุฏุฃ ุงูุจูุน ุญุชู ุจุฏูู ุฌูููุฑ ูุจูุฑ\nโข ุชุญููู ุฃูู ุฑุจุญ ุฑููู ุฎูุงู ูุชุฑุฉ ูุตูุฑุฉ\n\n๐ ุฅู ุทุจููุช ูุง ูููุ ูุณุชููู ุฃุฑุจุงุญู ุงููุงุฏูุฉ ูุณุฃูุฉ ููุช ููุท.\n\nโก ุชูููู:\nโข ุงูููุชุฌ ุฑููู ุจุงููุงูู (ุชุญููู ููุฑู ุจุนุฏ ุงูุฏูุน)\nโข ูุง ุชูุฌุฏ ูุณุฎ ูุฑููุฉ ุฃู ุดุญู ูุงุฏู\nโข ูุง ูููู ุงุณุชุฑุฌุงุน ุงููุจูุบ ุจุนุฏ ุงูุชุญููู ูุธุฑูุง ูุทุจูุนุฉ ุงูููุชุฌ ุงูุฑููู",
    "price": 39,
    "currency": "SAR",
    "download_url": "https://cix55jnodh8jj42w.public.blob.vercel-storage.com/%D8%A7%D9%84%D9%85%D9%86%D8%AA%D8%AC%D8%A7%D8%AA/%D8%A7%D9%84%D8%B1%D8%A8%D8%AD%20%D9%85%D9%86%20%D8%A7%D9%84%D9%85%D9%86%D8%AA%D8%AC%D8%A7%D8%AA%20%D8%A7%D9%84%D8%B1%D9%82%D9%85%D9%8A%D8%A9%20%E2%80%93%20%D9%85%D9%86%20%D8%A7%D9%84%D9%81%D9%83%D8%B1%D8%A9%20%D8%A5%D9%84%D9%89%20%D8%A3%D9%88%D9%84%20%D8%B1%D8%A8%D8%AD.pdf",
    "filename": "digital-products-profit.pdf",
    "file_size_mb": 8,
    "category": "ebooks",
    "tags": [
      "ุฑุจุญ",
      "ููุชุฌุงุช-ุฑูููุฉ",
      "ุชุณููู",
      "ุฏุฎู-ุณูุจู"
    ],
    "active": true,
    "rating": 4.9,
    "buyers": "ุนุฏุฏ ูุฑุงุช ุงูุดุฑุงุก: 129+",
    "featured": true,
    "originalPrice": 97.5
  },
  {
    "product_id": 3,
    "product_name": "15 ููุฑุฉ ูุดุฑูุน ุฑููู ูุฑุจุญ",
    "product_name_en": "15 Profitable Digital Project Ideas",
    "product_image": "/images/products/15-project-ideas.jpg",
    "description": "ูู ููุฑุช ููููุง ุชุจุฏุฃ ูุดุฑูุนู ุงูุฑูููุ ููู ูุง ุนุฑูุช ูู ููู ุชุจุฏุฃุ\nูุฐุง ุงููุชุงุจ ูู ุฏูููู ุงูุนููู ูุชุจุฏุฃ ูู ุงูุตูุฑ ูุชุจูู ูุตุฏุฑ ุฏุฎู ุญูููู ูู ุงูุฅูุชุฑูุช. ๐\n\nููุฏูู ูู ูุฐุง ุงููุชุงุจ ุฃูุซุฑ ูู 15 ููุฑุฉ ูุดุฑูุน ุฑููู ุฌุงูุฒุฉ ููุชูููุฐุ ุชูุฏุฑ ุชุจุฏุฃูุง ูู ุจูุชู ูุจุฏูู ุฑุฃุณ ูุงู ูุจูุฑุ ูุน ุดุฑุญ ูุงูู ููู ููุฑุฉ ุฎุทูุฉ ุจุฎุทูุฉ.\n\n๐ ุณุชุชุนูู ุฏุงุฎู ุงููุชุงุจ:\nโข ููู ุชุฎุชุงุฑ ุงูููุฑุฉ ุงูููุงุณุจุฉ ููุฏุฑุงุชู ูููุงุฑุงุชู\nโข ุฃุฏูุงุช ุจุณูุทุฉ ูุจุฏุก ูุดุฑูุนู ุฎูุงู ููู ูุงุญุฏ ููุท\nโข ุฃููุงุฑ ูุดุงุฑูุน ุฑูููุฉ ูุฌุฑูุจุฉ ุชุญูู ุฃุฑุจุงุญูุง ุญููููุฉ\nโข ุฎุทุฉ ุนูููุฉ ูุชูุณูุน ุฏุฎูู ูุชุทููุฑ ุนููู ุฃูููุงูู\nโข ุฃุณุฑุงุฑ ุงููุฌุงุญ ูู ุงูุชุณููู ุนุจุฑ TikTok ูInstagram ูYouTube\n\n๐ก ุฃูุซูุฉ ูู ุงููุดุงุฑูุน ุฏุงุฎู ุงููุชุงุจ:\nโข ุฅูุดุงุก ููุงุฉ YouTube ูุงุฌุญุฉ\nโข ุจูุน ุงูููุชุฌุงุช ุงูุฑูููุฉ (ูุชุจุ ููุงูุจุ ููุฑุณุงุช)\nโข ุงูุชุณููู ุจุงูุนูููุฉ (Affiliate Marketing)\nโข ุฅูุดุงุก ูุชุฌุฑ ุฅููุชุฑููู ุตุบูุฑ\nโข ุชูุฏูู ุฎุฏูุงุช ุงูุฐูุงุก ุงูุงุตุทูุงุนู\n\n๐ฏ ุงููุชูุฌุฉ ุงูููุงุฆูุฉ:\nุจุนุฏ ูุฑุงุกุฉ ูุฐุง ุงููุชุงุจุ ุณุชููู ูุงุฏุฑูุง ุนูู ุงุฎุชูุงุฑ ูุดุฑูุน ููุงุณุจูุ ุชุจุฏุฃ ููู ููุฑูุงุ ูุชุจูู ููู ูุตุฏุฑ ุฏุฎู ูุณุชูุฑ ูู ุงูุฅูุชุฑูุช.\n\n๐ฆ ูุง ุณุชุญุตู ุนููู ุนูุฏ ุงูุดุฑุงุก:\nโข ูุชุงุจ ุฑููู ุจุตูุบุฉ PDF ุชูุงุนูู ุฌุงูุฒ ููุชุญููู ุงูููุฑู\nโข ุชุตููู ุนุตุฑู ูุฑูุญ ูููุฑุงุกุฉ ุนูู ุงููุงุชู ุฃู ุงูููุจููุชุฑ\nโข ูุญุชูู ุชุทุจููู ูููุณ ูุธุฑู โ ููุงุณุจ ูููุจุชุฏุฆูู ูุงููุญุชุฑููู",
    "price": 57,
    "currency": "SAR",
    "download_url": "https://cix55jnodh8jj42w.public.blob.vercel-storage.com/%D8%A7%D9%84%D9%85%D9%86%D8%AA%D8%AC%D8%A7%D8%AA/15%20%D9%81%D9%83%D8%B1%D8%A9%20%D9%85%D8%B4%D8%B1%D9%88%D8%B9%20%D8%B1%D9%82%D9%85%D9%8A%20%D9%85%D8%B1%D8%A8%D8%AD%20%D9%8A%D9%85%D9%83%D9%86%D9%83%20%D8%A7%D9%84%D8%A8%D8%AF%D8%A1%20%D8%A8%D9%87%D8%A7%20%D9%85%D9%86%20%D8%A7%D9%84%D8%B5%D9%81%D8%B1%20%282%29.pdf",
    "filename": "15-project-ideas.pdf",
    "file_size_mb": 12,
    "category": "ebooks",
    "tags": [
      "ุฃููุงุฑ-ูุดุงุฑูุน",
      "ุฑูุงุฏุฉ-ุฃุนูุงู",
      "ูุดุงุฑูุน-ุฑูููุฉ",
      "ููุชููุจ",
      "ุชูู-ุชูู"
    ],
    "active": true,
    "rating": 4.7,
    "buyers": "ุนุฏุฏ ูุฑุงุช ุงูุดุฑุงุก: 200+",
    "featured": true,
    "originalPrice": 142.5
  },
  {
    "product_id": 4,
    "product_name": "ุจุงูุฉ ุงููููุชุงุฌ ุงูุงุญุชุฑุงููุฉ ๐ฌ",
    "product_name_en": "Professional Video Editing Pack",
    "product_image": "/images/products/ultimate-video-editing-pack.jpg",
    "description": "ุจุงูุฉ ุชุฌูุน ูู ูุง ูุญุชุงุฌู ุตุงูุน ุงููุญุชูู ุฃู ุงููุญุฑุฑ ุงููุญุชุฑู ูู ููุงู ูุงุญุฏ โ ูุคุซุฑุงุช ุตูุชูุฉุ ุฎูููุงุช ูุชุญุฑูุฉุ ุงูุชูุงูุงุชุ ููุทุงุช ููุฏูู ุงุญุชุฑุงููุฉ ูุงููุฒูุฏ!\n\nูู ุงููููุงุช ุฌุงูุฒุฉ ููุชุญููู ุงูููุฑู ุฏุงุฎู ููู ูุถุบูุท ูุงุญุฏ.\n\nุชู ุชุตููููุง ุฎุตูุตุงู ูุชุณุฑูุน ุนูููุฉ ุงููููุชุงุฌ ูุชุญุณูู ุฌูุฏุฉ ุงูุฅุฎุฑุงุฌ ูุฃู ููุฏูู ุณูุงุก ุนูู ููุชููุจุ ุชูู ุชููุ ุฃู ุฑููุฒ\n\n๐ฆ ุงููุญุชููุงุช:\n๐ง2000+ ูุคุซุฑุงุช ุตูุชูุฉ ุงุญุชุฑุงููุฉ\n\n๐ฅ 150+ ุงูุชูุงูุงุช ุฌุงูุฒุฉ ูุณูุณุฉ\n\n๐๏ธ 250+ ุฎูููุงุช ูุชุญุฑูุฉ ุฏููุงููููุฉ\n\n๐ผ๏ธ 200+ ููุงุทุน ูุตูุฑ B-Roll ุงุญุชุฑุงููุฉ\n\n๐ฌ200+ LUTs ุฃุตููุฉ ูุชุตุญูุญ ุงูุฃููุงู\n\nโจ 200+ ูุคุซุฑุงุช ุถูุฆูุฉ ููููุณูุงุช (Overlays & Textures)\n\nโ๏ธ 450+ ุงููุฑูุงู ุธูุงู ( Shadow Overlay)\n\n๐ ููุงุฐุง ูุฐุง ุงูููุชุฌ ูู ุงูุงูุถู ุจุงูุนุงูู ููุทููุจุ\nูุฃู ุฃุบูุจ ุตูุงุน ุงููุญุชูู ุงูุฌุฏุฏ ูุนุงููู ูู ููุฉ ุงูุฃุฏูุงุช ุงูุฌุงูุฒุฉ ูููููุชุงุฌ\nูุฐู ุงูุญุฒูุฉ ุชููุฑ ููู ูู ุดูุก ุฌุงูุฒ ุจุฌูุฏุฉ ุนุงููุฉ ุฏูู ุงูุญุงุฌุฉ ููุจุญุซ ุงููุชุนุจ ุฃู ุงูุงุดุชุฑุงู ุงูุดูุฑู\nุงูููุชุฌ ุฑููู ุจุงููุงูู (ูุง ูุญุชุงุฌ ุชูุงููู ุฅุถุงููุฉ)\n\nโก ุชุญุฏูุซุงุช ูุฌุงููุฉ ูุณุชูุฑุฉ\nูุฐู ูู ุงูุญุฒูุฉ ุงููุญูุฏุฉ ุงูุชู ุชุณุชูุฑ ูู ุงูุชุญุฏูุซ ุจุนุฏ ุงูุดุฑุงุก!\n\nูู ูู ูุดุชุฑู ุงูุจุงูุฉ ูุญุตู ุนูู ุชุญุฏูุซุงุช ูุฌุงููุฉ ูุฏู ุงูุญูุงุฉ ุชุชุถูู ุฃุตูููุง ุฌุฏูุฏุฉ (Assets) ูุชู ุฅุถุงูุชูุง ุจุงูุชุธุงู.\n\n๐ฐ ุณูุงุณุฉ ุงูุงุณุชุฑุฌุงุน\nุฌููุน ุงููุจูุนุงุช ููุงุฆูุฉ.\n\nูุธุฑูุง ูุทุจูุนุฉ ุงูููุชุฌ ุงูุฑููู ูุฅููุงููุฉ ุชุญูููู ูุจุงุดุฑุฉ ุจุนุฏ ุงูุดุฑุงุกุ ูุง ูููู ุชูุฏูู ุงุณุชุฑุฌุงุน ุฃู ุฅูุบุงุก ุจุนุฏ ุงูุฏูุน.\n\nโ๏ธ ุญููู ุงูุงุณุชุฎุฏุงู\nููุณูุญ ุจุงุณุชุฎุฏุงู ูุฐู ุงููููุงุช ูู ุงููุดุงุฑูุน ุงูุดุฎุตูุฉ ูุงูุชุฌุงุฑูุฉ (ูุซู ุงูููุฏูููุงุชุ ุงูุฅุนูุงูุงุชุ ุงููุญุชูู ุงูุฑููู).\n\nููููุน ููุนูุง ุจุงุชูุง ุฅุนุงุฏุฉ ุจูุน ุฃู ุชูุฒูุน ุงููููุงุช ุจุฃู ุดููุ ูุณูุชู ุงุชุฎุงุฐ ุฅุฌุฑุงุกุงุช ูุงููููุฉ ุถุฏ ุฃู ุงูุชูุงู.",
    "price": 24.99,
    "originalPrice": 119.99,
    "currency": "SAR",
    "download_url": "https://example.com/downloads/ultimate-video-editing-pack.zip",
    "filename": "ultimate-video-editing-pack.zip",
    "file_size_mb": 14000,
    "category": "editing-tools",
    "tags": [
      "ูุคุซุฑุงุช-ุตูุชูุฉ",
      "ุฎูููุงุช-ูุชุญุฑูุฉ",
      "ุงูุชูุงูุงุช",
      "ุชูู-ุชูู",
      "ุฑููุฒ",
      "ุงุญุชุฑุงูู",
      "ูููุชุงุฌ"
    ],
    "active": true,
    "rating": 4.9,
    "buyers": "ุนุฏุฏ ูุฑุงุช ุงูุดุฑุงุก: 25+",
    "featured": true,
    "isFree": false
  },
  {
    "product_id": 5,
    "product_name": "ุญุฒูุฉ ุฃููููุงุช ูุชุญุฑูุฉ",
    "product_name_en": "Animated Icons Pack",
    "product_image": "/images/products/icons-pack-placeholder.jpg",
    "description": "ูุฌููุนุฉ ุฃููููุงุช ููุดู ุฌุฑุงููู ุฌุงูุฒุฉ ููุงุณุชุฎุฏุงู ูู ุงูููุฏูููุงุช (ุงุดุชุฑุงู โ ูุงูู โ ุฌุฑุณ โ ุชูุงุนู).\n\n๐ฌ ูุญุชููุงุช ุงูุญุฒูุฉ:\nโข 20+ ุฃููููุฉ ุงุดุชุฑุงู ูุชุญุฑูุฉ\nโข 15+ ุฃููููุฉ ูุงูู ูุฏูุณูุงูู\nโข 10+ ุฃููููุฉ ุฌุฑุณ ุงูุชูุจููุงุช\nโข 25+ ุฃููููุฉ ุชูุงุนู (ุชุนูููุ ูุดุงุฑูุฉุ ุญูุธ)\nโข 15+ ุฃููููุฉ ูุณุงุฆู ุงูุชูุงุตู ุงูุงุฌุชูุงุนู\nโข 20+ ุฃููููุฉ ุฃุฑูุงู ูุฅุญุตุงุฆูุงุช ูุชุญุฑูุฉ\nโข 10+ ุฃููููุฉ ุฃุณูู ูุงุชุฌุงูุงุช\n\nโก ุงูููุงุตูุงุช ุงูุชูููุฉ:\nโข ุฏูุฉ ุนุงููุฉ ุงูุฌูุฏุฉ\nโข ูุนุฏู ุฅุทุงุฑุงุช 30/60 FPS\nโข ุฎูููุฉ ุดูุงูุฉ (Alpha Channel)\nโข ูุฏุฉ ุงูุญุฑูุฉ 2-5 ุซูุงูู\nโข ุญููุฉ ูุณุชูุฑุฉ (Loop)\n\n๐ ุตูุบ ุงููููุงุช:\nโข MP4 (ููุงุณุชุฎุฏุงู ุงููุจุงุดุฑ)\nโข MOV (ุจุฎูููุฉ ุดูุงูุฉ)\nโข GIF (ููููุจ ูุงูููุงูุน)\nโข After Effects Project Files\n\n๐จ ุฃููุงุท ูุชููุนุฉ:\nโข ุฃุณููุจ ูุณุทุญ (Flat Design)\nโข ุฃุณููุจ ุซูุงุซู ุงูุฃุจุนุงุฏ (3D Style)\nโข ุฃุณููุจ ุฑุณูู ูุชุญุฑูุฉ (Cartoon)\nโข ุฃุณููุจ ุงุญุชุฑุงูู (Corporate)\n\n๐๏ธ ูุชูุงูู ูุน:\nโข Adobe Premiere Pro\nโข Final Cut Pro\nโข DaVinci Resolve\nโข After Effects\nโข Camtasia\nโข ุฌููุน ุจุฑุงูุฌ ุงููููุชุงุฌ ุงูุดููุฑุฉ\n\n๐ก ุงุณุชุฎุฏุงูุงุช ูุซุงููุฉ:\nโข ููุฏูููุงุช ููุชููุจ\nโข ุงููุญุชูู ุงูุชุนูููู\nโข ุงูููุฏูููุงุช ุงูุชุณููููุฉ\nโข ุงูุนุฑูุถ ุงูุชูุฏูููุฉ\nโข ูุญุชูู ูุณุงุฆู ุงูุชูุงุตู ุงูุงุฌุชูุงุนู\n\nโจ ูููุฒุงุช ุฎุงุตุฉ:\n๐ฏ ุฌูุฏุฉ ุงุญุชุฑุงููุฉ ุนุงููุฉ\nโก ุณูููุฉ ุงูุงุณุชุฎุฏุงู\n๐จ ุฃููุงู ูุงุจูุฉ ููุชุฎุตูุต\n๐ฑ ููุงุณุจุฉ ูุฌููุน ุฃุญุฌุงู ุงูุดุงุดุงุช\n๐ ุฏููู ุงูุงุณุชุฎุฏุงู ูุฑูู\n\n๐ฅ ุงูุชุณููู ููุฑู ุจุนุฏ ุงูุฏูุน\n๐ ุงูุตูุบุฉ: ูููุงุช ูุถุบูุทุฉ ZIP\n๐พ ุงูุญุฌู: ุชูุฑูุจุงู 1.2 ุฌูุฌุงุจุงูุช",
    "price": 7.99,
    "originalPrice": 35,
    "currency": "SAR",
    "download_url": "https://example.com/downloads/animated-icons-pack.zip",
    "filename": "animated-icons-pack.zip",
    "file_size_mb": 3000,
    "category": "youtube-tools",
    "tags": [
      "ุฃููููุงุช",
      "ูุชุญุฑูุฉ",
      "ููุดู-ุฌุฑุงููู",
      "ููุชููุจ",
      "ุชูุงุนู"
    ],
    "active": true,
    "rating": 4.8,
    "buyers": "ุนุฏุฏ ูุฑุงุช ุงูุดุฑุงุก: 300+",
    "featured": true,
    "isFree": false
  },
  {
    "product_id": 6,
    "product_name": "ุจุงูุฉ ุงูุชุตููู ูุตูุงุนุฉ ุงููุญุชูู",
    "product_name_en": "Design and Content Creation Pack",
    "product_image": "/images/products/design-content-pack.jpg",
    "description": "ุจุงูุฉ ุดุงููุฉ ููุชุตููู ูุตูุงุนุฉ ุงููุญุชูู ุชุญุชูู ุนูู ูู ูุง ุชุญุชุงุฌู ูุฅูุดุงุก ูุญุชูู ุงุญุชุฑุงูู ูููุฒ.\n\n๐จ ูุญุชููุงุช ุงูุจุงูุฉ:\n\nโข ุฃููููุงุช ูุชุญุฑูุฉ ุนุงููุฉ ุงูุฌูุฏุฉ\nโข 1100 ุฃููููุฉ PNG ุดูุงูุฉ ุจุฌูุฏุฉ ุนุงููุฉ\nโข ุชุฃุซูุฑุงุช ูุตูุต ุงุญุชุฑุงููุฉ (Text Effects)\nโข ุฃูุซุฑ ูู 50 ุฎุท ูููุฒ ูุฌุงูุฒ ููุงุณุชุฎุฏุงู (OTF/TTF)\nโข ููุงูุจ ุฌุงูุฒุฉ ููุณูุดุงู ููุฏูุง ุจุตูุบ ูุฎุชููุฉ (ุจูุง ูููุง PSD)\nโข ูููุงุช ูุงููุฉ ุชุณุงุนุฏ ุนูู ุจูุงุก ุตูุฑุฉ Thumbnail ููููุชููุจ ูู ุงูุตูุฑ\n\nโจ ุงูููุฒุงุช:\nโข ุฌูุฏุฉ ุงุญุชุฑุงููุฉ ุนุงููุฉ\nโข ุณูููุฉ ุงูุงุณุชุฎุฏุงู\nโข ูุชูุงูู ูุน ุฌููุน ุจุฑุงูุฌ ุงูุชุตููู\nโข ููุงูุจ ูุงุจูุฉ ููุชุฎุตูุต\nโข ุฏููู ุงูุงุณุชุฎุฏุงู ูุฑูู\n\n๐๏ธ ูุชูุงูู ูุน:\nโข Adobe Photoshop\nโข Adobe Illustrator\nโข Canva\nโข Figma\nโข ุฌููุน ุจุฑุงูุฌ ุงูุชุตููู ุงูุดููุฑุฉ\n\n๐ก ุงุณุชุฎุฏุงูุงุช ูุซุงููุฉ:\nโข ุชุตููู ูุญุชูู ุงูุณูุดุงู ููุฏูุง\nโข ุฅูุดุงุก Thumbnails ููููุชููุจ\nโข ุชุตููู ุงูุจูุณุชุงุช ูุงูุฅุนูุงูุงุช\nโข ุงููุญุชูู ุงูุชุนูููู ูุงูุชุณูููู\nโข ุงูุนุฑูุถ ุงูุชูุฏูููุฉ\n\n๐ฆ ุงูุชุณููู ููุฑู ุจุนุฏ ุงูุฏูุน\n๐ ุงูุตูุบุฉ: ูููุงุช ูุถุบูุทุฉ ZIP\n๐พ ุงูุญุฌู: ุชูุฑูุจุงู 2.5 ุฌูุฌุงุจุงูุช",
    "price": 29.99,
    "originalPrice": 149.99,
    "currency": "SAR",
    "download_url": "https://example.com/downloads/design-content-pack.zip",
    "filename": "design-content-pack.zip",
    "file_size_mb": 2500,
    "category": "editing-tools",
    "tags": [
      "ุชุตููู",
      "ูุญุชูู",
      "ุฃููููุงุช",
      "ุฎุทูุท",
      "ููุงูุจ",
      "ุณูุดุงู-ููุฏูุง",
      "ููุชููุจ"
    ],
    "active": true,
    "rating": 4.9,
    "buyers": "ุนุฏุฏ ูุฑุงุช ุงูุดุฑุงุก: 90",
    "featured": true,
    "isFree": false
  }
]
